waterqsvg/__init__.py
waterqsvg/_version.py
waterqsvg/unified_interface.py
waterqsvg/config/__init__.py
waterqsvg/config/grid_config.py
waterqsvg/config/indicators.py
waterqsvg/core/__init__.py
waterqsvg/core/downloader.py
waterqsvg/core/extractor.py
waterqsvg/data/__init__.py
waterqsvg/data/parser.py
waterqsvg/data/standardizer.py
waterqsvg/data/validator.py
waterqsvg/interpolation/__init__.py
waterqsvg/interpolation/alpha_shape.py
waterqsvg/interpolation/convex_hull.py
waterqsvg/interpolation/density_boundary.py
waterqsvg/interpolation/enhanced_interpolation.py
waterqsvg/interpolation/kml_boundary.py
waterqsvg/interpolation/kriging_interpolation.py
waterqsvg/utils/__init__.py
waterqsvg/utils/logger.py
waterqsvg/visualization/__init__.py
waterqsvg/visualization/color_mapper.py
waterqsvg/visualization/colorbar_generator.py
waterqsvg/visualization/layout_calculator.py
waterqsvg/visualization/svg_generator.py
waterqsvg-1.3.2.dist-info/METADATA
waterqsvg-1.3.2.dist-info/WHEEL
waterqsvg-1.3.2.dist-info/entry_points.txt
waterqsvg-1.3.2.dist-info/top_level.txt
waterqsvg-1.3.2.dist-info/RECORD
