Metadata-Version: 2.4
Name: waterqsvg
Version: 1.3.2
Summary: 专用于从水质监测数据生成SVG热力图的独立Python库
Author-email: Water Quality Monitoring Team <team@example.com>
License-Expression: MIT
Project-URL: Homepage, https://github.com/1034378361/waterqsvg
Project-URL: Repository, https://github.com/1034378361/waterqsvg
Project-URL: Documentation, https://github.com/1034378361/waterqsvg#readme
Project-URL: Issues, https://github.com/1034378361/waterqsvg/issues
Keywords: water-quality,svg,heatmap,environmental,monitoring
Classifier: Development Status :: 4 - Beta
Classifier: Intended Audience :: Science/Research
Classifier: Topic :: Scientific/Engineering :: Visualization
Classifier: Topic :: Scientific/Engineering :: GIS
Classifier: Programming Language :: Python :: 3
Classifier: Programming Language :: Python :: 3.11
Classifier: Programming Language :: Python :: 3.12
Requires-Python: >=3.11
Requires-Dist: chardet>=5.2.0
Requires-Dist: matplotlib>=3.10.3
Requires-Dist: numpy>=2.3.1
Requires-Dist: oss2>=2.19.1
Requires-Dist: pandas>=2.3.1
Requires-Dist: pillow>=11.3.0
Requires-Dist: pykrige>=1.7.0
Requires-Dist: python-dotenv>=1.1.1
Requires-Dist: requests>=2.32.4
Requires-Dist: scipy>=1.16.0
Requires-Dist: setuptools-scm>=8.3.1
